{
  "name": "chunk_2087360595_10",
  "properties": {
    "uuid": {
      "value": 6867852291431105087
    },
    "name": {
      "value": "chunk_2087360595_10"
    },
    "category": {
      "value": "Minecraft Import"
    },
    "palette": {
      "values": [
        {
          "color": 4294901760,
          "materialParameters": 255,
          "emissive": 0,
          "blockBaseImageName": "",
          "blockType": 0,
          "metadataNote": "invalid_marker"
        },
        {
          "color": 4283650899,
          "materialParameters": 255,
          "emissive": 0,
          "blockBaseImageName": "mc_bedrock",
          "blockType": 0,
          "metadataNote": "bedrock"
        },
        {
          "color": 4286414205,
          "materialParameters": 255,
          "emissive": 0,
          "blockBaseImageName": "mc_deepslate",
          "blockType": 0,
          "metadataNote": "deepslate"
        },
        {
          "color": 4286680207,
          "materialParameters": 255,
          "emissive": 0,
          "blockBaseImageName": "mc_deepslate_diamond_ore",
          "blockType": 0,
          "metadataNote": "deepslate_diamond_ore"
        },
        {
          "color": 4286868331,
          "materialParameters": 255,
          "emissive": 0,
          "blockBaseImageName": "mc_deepslate_redstone_ore",
          "blockType": 0,
          "metadataNote": "deepslate_redstone_ore"
        },
        {
          "color": 4287597436,
          "materialParameters": 255,
          "emissive": 0,
          "blockBaseImageName": "mc_deepslate_gold_ore",
          "blockType": 0,
          "metadataNote": "deepslate_gold_ore"
        },
        {
          "color": 4284903558,
          "materialParameters": 255,
          "emissive": 0,
          "blockBaseImageName": "mc_deepslate_lapis_ore",
          "blockType": 0,
          "metadataNote": "deepslate_lapis_ore"
        },
        {
          "color": 4286414205,
          "materialParameters": 255,
          "emissive": 0,
          "blockBaseImageName": "mc_tuff",
          "blockType": 0,
          "metadataNote": "tuff"
        },
        {
          "color": 4287070846,
          "materialParameters": 255,
          "emissive": 0,
          "blockBaseImageName": "mc_deepslate_iron_ore",
          "blockType": 0,
          "metadataNote": "deepslate_iron_ore"
        },
        {
          "color": 4286479482,
          "materialParameters": 255,
          "emissive": 0,
          "blockBaseImageName": "mc_gravel",
          "blockType": 0,
          "metadataNote": "gravel"
        },
        {
          "color": 4286414205,
          "materialParameters": 255,
          "emissive": 0,
          "blockBaseImageName": "mc_diorite",
          "blockType": 0,
          "metadataNote": "diorite"
        },
        {
          "color": 4286414205,
          "materialParameters": 255,
          "emissive": 0,
          "blockBaseImageName": "mc_granite",
          "blockType": 0,
          "metadataNote": "granite"
        },
        {
          "color": 4286414205,
          "materialParameters": 255,
          "emissive": 0,
          "blockBaseImageName": "mc_sculk",
          "blockType": 0,
          "metadataNote": "sculk"
        },
        {
          "color": 4286414205,
          "materialParameters": 255,
          "emissive": 0,
          "blockBaseImageName": "mc_sculk_vein",
          "blockType": 0,
          "metadataNote": "sculk_vein"
        },
        {
          "color": 4286414205,
          "materialParameters": 255,
          "emissive": 0,
          "blockBaseImageName": "mc_sculk_sensor",
          "blockType": 0,
          "metadataNote": "sculk_sensor"
        },
        {
          "color": 4286414205,
          "materialParameters": 255,
          "emissive": 0,
          "blockBaseImageName": "mc_raw_iron_block",
          "blockType": 0,
          "metadataNote": "raw_iron_block"
        },
        {
          "color": 4286414205,
          "materialParameters": 255,
          "emissive": 0,
          "blockBaseImageName": "mc_andesite",
          "blockType": 0,
          "metadataNote": "andesite"
        },
        {
          "color": 4286414205,
          "materialParameters": 255,
          "emissive": 0,
          "blockBaseImageName": "mc_sculk_shrieker",
          "blockType": 0,
          "metadataNote": "sculk_shrieker"
        },
        {
          "color": 4286414205,
          "materialParameters": 255,
          "emissive": 0,
          "blockBaseImageName": "mc_sculk_catalyst",
          "blockType": 0,
          "metadataNote": "sculk_catalyst"
        },
        {
          "color": 4286216826,
          "materialParameters": 255,
          "emissive": 0,
          "blockBaseImageName": "mc_cobblestone",
          "blockType": 0,
          "metadataNote": "cobblestone"
        },
        {
          "color": 4284843877,
          "materialParameters": 255,
          "emissive": 0,
          "blockBaseImageName": "mc_mossy_cobblestone",
          "blockType": 0,
          "metadataNote": "mossy_cobblestone"
        },
        {
          "color": 4286414205,
          "materialParameters": 255,
          "emissive": 0,
          "blockBaseImageName": "mc_glow_lichen",
          "blockType": 0,
          "metadataNote": "glow_lichen"
        },
        {
          "color": 4286414205,
          "materialParameters": 255,
          "emissive": 0,
          "blockBaseImageName": "mc_deepslate_copper_ore",
          "blockType": 0,
          "metadataNote": "deepslate_copper_ore"
        },
        {
          "color": 4286414205,
          "materialParameters": 255,
          "emissive": 0,
          "blockBaseImageName": "mc_copper_ore",
          "blockType": 0,
          "metadataNote": "copper_ore"
        },
        {
          "color": 4292106770,
          "materialParameters": 255,
          "emissive": 0,
          "blockBaseImageName": "mc_lava",
          "blockType": 0,
          "metadataNote": "lava"
        },
        {
          "color": 4286414205,
          "materialParameters": 255,
          "emissive": 0,
          "blockBaseImageName": "mc_smooth_basalt",
          "blockType": 0,
          "metadataNote": "smooth_basalt"
        },
        {
          "color": 4286414205,
          "materialParameters": 255,
          "emissive": 0,
          "blockBaseImageName": "mc_calcite",
          "blockType": 0,
          "metadataNote": "calcite"
        },
        {
          "color": 4279904049,
          "materialParameters": 255,
          "emissive": 0,
          "blockBaseImageName": "mc_spawner",
          "blockType": 0,
          "metadataNote": "spawner"
        },
        {
          "color": 4285575132,
          "materialParameters": 255,
          "emissive": 0,
          "blockBaseImageName": "mc_water",
          "blockType": 0,
          "metadataNote": "water"
        },
        {
          "color": 4286996547,
          "materialParameters": 255,
          "emissive": 0,
          "blockBaseImageName": "mc_dirt",
          "blockType": 0,
          "metadataNote": "dirt"
        },
        {
          "color": 4286414205,
          "materialParameters": 255,
          "emissive": 0,
          "blockBaseImageName": "mc_amethyst_block",
          "blockType": 0,
          "metadataNote": "amethyst_block"
        },
        {
          "color": 4286414205,
          "materialParameters": 255,
          "emissive": 0,
          "blockBaseImageName": "mc_budding_amethyst",
          "blockType": 0,
          "metadataNote": "budding_amethyst"
        },
        {
          "color": 4286414205,
          "materialParameters": 255,
          "emissive": 0,
          "blockBaseImageName": "mc_small_amethyst_bud",
          "blockType": 0,
          "metadataNote": "small_amethyst_bud"
        },
        {
          "color": 4286414205,
          "materialParameters": 255,
          "emissive": 0,
          "blockBaseImageName": "mc_large_amethyst_bud",
          "blockType": 0,
          "metadataNote": "large_amethyst_bud"
        },
        {
          "color": 4286414205,
          "materialParameters": 255,
          "emissive": 0,
          "blockBaseImageName": "mc_amethyst_cluster",
          "blockType": 0,
          "metadataNote": "amethyst_cluster"
        },
        {
          "color": 4286414205,
          "materialParameters": 255,
          "emissive": 0,
          "blockBaseImageName": "mc_medium_amethyst_bud",
          "blockType": 0,
          "metadataNote": "medium_amethyst_bud"
        },
        {
          "color": 4286868331,
          "materialParameters": 255,
          "emissive": 0,
          "blockBaseImageName": "mc_redstone_ore",
          "blockType": 0,
          "metadataNote": "redstone_ore"
        },
        {
          "color": 4283124555,
          "materialParameters": 255,
          "emissive": 0,
          "blockBaseImageName": "",
          "blockType": 0,
          "metadataNote": ""
        },
        {
          "color": 4283124555,
          "materialParameters": 255,
          "emissive": 0,
          "blockBaseImageName": "",
          "blockType": 0,
          "metadataNote": ""
        },
        {
          "color": 4283124555,
          "materialParameters": 255,
          "emissive": 0,
          "blockBaseImageName": "",
          "blockType": 0,
          "metadataNote": ""
        },
        {
          "color": 4283124555,
          "materialParameters": 255,
          "emissive": 0,
          "blockBaseImageName": "",
          "blockType": 0,
          "metadataNote": ""
        },
        {
          "color": 4283124555,
          "materialParameters": 255,
          "emissive": 0,
          "blockBaseImageName": "",
          "blockType": 0,
          "metadataNote": ""
        },
        {
          "color": 4283124555,
          "materialParameters": 255,
          "emissive": 0,
          "blockBaseImageName": "",
          "blockType": 0,
          "metadataNote": ""
        },
        {
          "color": 4283124555,
          "materialParameters": 255,
          "emissive": 0,
          "blockBaseImageName": "",
          "blockType": 0,
          "metadataNote": ""
        },
        {
          "color": 4283124555,
          "materialParameters": 255,
          "emissive": 0,
          "blockBaseImageName": "",
          "blockType": 0,
          "metadataNote": ""
        },
        {
          "color": 4283124555,
          "materialParameters": 255,
          "emissive": 0,
          "blockBaseImageName": "",
          "blockType": 0,
          "metadataNote": ""
        },
        {
          "color": 4283124555,
          "materialParameters": 255,
          "emissive": 0,
          "blockBaseImageName": "",
          "blockType": 0,
          "metadataNote": ""
        },
        {
          "color": 4283124555,
          "materialParameters": 255,
          "emissive": 0,
          "blockBaseImageName": "",
          "blockType": 0,
          "metadataNote": ""
        },
        {
          "color": 4283124555,
          "materialParameters": 255,
          "emissive": 0,
          "blockBaseImageName": "",
          "blockType": 0,
          "metadataNote": ""
        },
        {
          "color": 4283124555,
          "materialParameters": 255,
          "emissive": 0,
          "blockBaseImageName": "",
          "blockType": 0,
          "metadataNote": ""
        },
        {
          "color": 4283124555,
          "materialParameters": 255,
          "emissive": 0,
          "blockBaseImageName": "",
          "blockType": 0,
          "metadataNote": ""
        },
        {
          "color": 4283124555,
          "materialParameters": 255,
          "emissive": 0,
          "blockBaseImageName": "",
          "blockType": 0,
          "metadataNote": ""
        },
        {
          "color": 4283124555,
          "materialParameters": 255,
          "emissive": 0,
          "blockBaseImageName": "",
          "blockType": 0,
          "metadataNote": ""
        },
        {
          "color": 4283124555,
          "materialParameters": 255,
          "emissive": 0,
          "blockBaseImageName": "",
          "blockType": 0,
          "metadataNote": ""
        },
        {
          "color": 4283124555,
          "materialParameters": 255,
          "emissive": 0,
          "blockBaseImageName": "",
          "blockType": 0,
          "metadataNote": ""
        },
        {
          "color": 4283124555,
          "materialParameters": 255,
          "emissive": 0,
          "blockBaseImageName": "",
          "blockType": 0,
          "metadataNote": ""
        },
        {
          "color": 4283124555,
          "materialParameters": 255,
          "emissive": 0,
          "blockBaseImageName": "",
          "blockType": 0,
          "metadataNote": ""
        },
        {
          "color": 4283124555,
          "materialParameters": 255,
          "emissive": 0,
          "blockBaseImageName": "",
          "blockType": 0,
          "metadataNote": ""
        },
        {
          "color": 4283124555,
          "materialParameters": 255,
          "emissive": 0,
          "blockBaseImageName": "",
          "blockType": 0,
          "metadataNote": ""
        },
        {
          "color": 4283124555,
          "materialParameters": 255,
          "emissive": 0,
          "blockBaseImageName": "",
          "blockType": 0,
          "metadataNote": ""
        },
        {
          "color": 4283124555,
          "materialParameters": 255,
          "emissive": 0,
          "blockBaseImageName": "",
          "blockType": 0,
          "metadataNote": ""
        },
        {
          "color": 4283124555,
          "materialParameters": 255,
          "emissive": 0,
          "blockBaseImageName": "",
          "blockType": 0,
          "metadataNote": ""
        },
        {
          "color": 4283124555,
          "materialParameters": 255,
          "emissive": 0,
          "blockBaseImageName": "",
          "blockType": 0,
          "metadataNote": ""
        },
        {
          "color": 4283124555,
          "materialParameters": 255,
          "emissive": 0,
          "blockBaseImageName": "",
          "blockType": 0,
          "metadataNote": ""
        },
        {
          "color": 4283124555,
          "materialParameters": 255,
          "emissive": 0,
          "blockBaseImageName": "",
          "blockType": 0,
          "metadataNote": ""
        },
        {
          "color": 4283124555,
          "materialParameters": 255,
          "emissive": 0,
          "blockBaseImageName": "",
          "blockType": 0,
          "metadataNote": ""
        },
        {
          "color": 4283124555,
          "materialParameters": 255,
          "emissive": 0,
          "blockBaseImageName": "",
          "blockType": 0,
          "metadataNote": ""
        },
        {
          "color": 4283124555,
          "materialParameters": 255,
          "emissive": 0,
          "blockBaseImageName": "",
          "blockType": 0,
          "metadataNote": ""
        },
        {
          "color": 4283124555,
          "materialParameters": 255,
          "emissive": 0,
          "blockBaseImageName": "",
          "blockType": 0,
          "metadataNote": ""
        },
        {
          "color": 4283124555,
          "materialParameters": 255,
          "emissive": 0,
          "blockBaseImageName": "",
          "blockType": 0,
          "metadataNote": ""
        },
        {
          "color": 4283124555,
          "materialParameters": 255,
          "emissive": 0,
          "blockBaseImageName": "",
          "blockType": 0,
          "metadataNote": ""
        },
        {
          "color": 4283124555,
          "materialParameters": 255,
          "emissive": 0,
          "blockBaseImageName": "",
          "blockType": 0,
          "metadataNote": ""
        },
        {
          "color": 4283124555,
          "materialParameters": 255,
          "emissive": 0,
          "blockBaseImageName": "",
          "blockType": 0,
          "metadataNote": ""
        },
        {
          "color": 4283124555,
          "materialParameters": 255,
          "emissive": 0,
          "blockBaseImageName": "",
          "blockType": 0,
          "metadataNote": ""
        },
        {
          "color": 4283124555,
          "materialParameters": 255,
          "emissive": 0,
          "blockBaseImageName": "",
          "blockType": 0,
          "metadataNote": ""
        },
        {
          "color": 4283124555,
          "materialParameters": 255,
          "emissive": 0,
          "blockBaseImageName": "",
          "blockType": 0,
          "metadataNote": ""
        },
        {
          "color": 4283124555,
          "materialParameters": 255,
          "emissive": 0,
          "blockBaseImageName": "",
          "blockType": 0,
          "metadataNote": ""
        },
        {
          "color": 4283124555,
          "materialParameters": 255,
          "emissive": 0,
          "blockBaseImageName": "",
          "blockType": 0,
          "metadataNote": ""
        },
        {
          "color": 4283124555,
          "materialParameters": 255,
          "emissive": 0,
          "blockBaseImageName": "",
          "blockType": 0,
          "metadataNote": ""
        },
        {
          "color": 4283124555,
          "materialParameters": 255,
          "emissive": 0,
          "blockBaseImageName": "",
          "blockType": 0,
          "metadataNote": ""
        },
        {
          "color": 4283124555,
          "materialParameters": 255,
          "emissive": 0,
          "blockBaseImageName": "",
          "blockType": 0,
          "metadataNote": ""
        },
        {
          "color": 4283124555,
          "materialParameters": 255,
          "emissive": 0,
          "blockBaseImageName": "",
          "blockType": 0,
          "metadataNote": ""
        },
        {
          "color": 4283124555,
          "materialParameters": 255,
          "emissive": 0,
          "blockBaseImageName": "",
          "blockType": 0,
          "metadataNote": ""
        },
        {
          "color": 4283124555,
          "materialParameters": 255,
          "emissive": 0,
          "blockBaseImageName": "",
          "blockType": 0,
          "metadataNote": ""
        },
        {
          "color": 4283124555,
          "materialParameters": 255,
          "emissive": 0,
          "blockBaseImageName": "",
          "blockType": 0,
          "metadataNote": ""
        },
        {
          "color": 4283124555,
          "materialParameters": 255,
          "emissive": 0,
          "blockBaseImageName": "",
          "blockType": 0,
          "metadataNote": ""
        },
        {
          "color": 4283124555,
          "materialParameters": 255,
          "emissive": 0,
          "blockBaseImageName": "",
          "blockType": 0,
          "metadataNote": ""
        },
        {
          "color": 4283124555,
          "materialParameters": 255,
          "emissive": 0,
          "blockBaseImageName": "",
          "blockType": 0,
          "metadataNote": ""
        },
        {
          "color": 4283124555,
          "materialParameters": 255,
          "emissive": 0,
          "blockBaseImageName": "",
          "blockType": 0,
          "metadataNote": ""
        },
        {
          "color": 4283124555,
          "materialParameters": 255,
          "emissive": 0,
          "blockBaseImageName": "",
          "blockType": 0,
          "metadataNote": ""
        },
        {
          "color": 4283124555,
          "materialParameters": 255,
          "emissive": 0,
          "blockBaseImageName": "",
          "blockType": 0,
          "metadataNote": ""
        },
        {
          "color": 4283124555,
          "materialParameters": 255,
          "emissive": 0,
          "blockBaseImageName": "",
          "blockType": 0,
          "metadataNote": ""
        },
        {
          "color": 4283124555,
          "materialParameters": 255,
          "emissive": 0,
          "blockBaseImageName": "",
          "blockType": 0,
          "metadataNote": ""
        },
        {
          "color": 4283124555,
          "materialParameters": 255,
          "emissive": 0,
          "blockBaseImageName": "",
          "blockType": 0,
          "metadataNote": ""
        },
        {
          "color": 4283124555,
          "materialParameters": 255,
          "emissive": 0,
          "blockBaseImageName": "",
          "blockType": 0,
          "metadataNote": ""
        },
        {
          "color": 4283124555,
          "materialParameters": 255,
          "emissive": 0,
          "blockBaseImageName": "",
          "blockType": 0,
          "metadataNote": ""
        },
        {
          "color": 4283124555,
          "materialParameters": 255,
          "emissive": 0,
          "blockBaseImageName": "",
          "blockType": 0,
          "metadataNote": ""
        },
        {
          "color": 4283124555,
          "materialParameters": 255,
          "emissive": 0,
          "blockBaseImageName": "",
          "blockType": 0,
          "metadataNote": ""
        },
        {
          "color": 4283124555,
          "materialParameters": 255,
          "emissive": 0,
          "blockBaseImageName": "",
          "blockType": 0,
          "metadataNote": ""
        },
        {
          "color": 4283124555,
          "materialParameters": 255,
          "emissive": 0,
          "blockBaseImageName": "",
          "blockType": 0,
          "metadataNote": ""
        },
        {
          "color": 4283124555,
          "materialParameters": 255,
          "emissive": 0,
          "blockBaseImageName": "",
          "blockType": 0,
          "metadataNote": ""
        },
        {
          "color": 4283124555,
          "materialParameters": 255,
          "emissive": 0,
          "blockBaseImageName": "",
          "blockType": 0,
          "metadataNote": ""
        },
        {
          "color": 4283124555,
          "materialParameters": 255,
          "emissive": 0,
          "blockBaseImageName": "",
          "blockType": 0,
          "metadataNote": ""
        },
        {
          "color": 4283124555,
          "materialParameters": 255,
          "emissive": 0,
          "blockBaseImageName": "",
          "blockType": 0,
          "metadataNote": ""
        },
        {
          "color": 4283124555,
          "materialParameters": 255,
          "emissive": 0,
          "blockBaseImageName": "",
          "blockType": 0,
          "metadataNote": ""
        },
        {
          "color": 4283124555,
          "materialParameters": 255,
          "emissive": 0,
          "blockBaseImageName": "",
          "blockType": 0,
          "metadataNote": ""
        },
        {
          "color": 4283124555,
          "materialParameters": 255,
          "emissive": 0,
          "blockBaseImageName": "",
          "blockType": 0,
          "metadataNote": ""
        },
        {
          "color": 4283124555,
          "materialParameters": 255,
          "emissive": 0,
          "blockBaseImageName": "",
          "blockType": 0,
          "metadataNote": ""
        },
        {
          "color": 4283124555,
          "materialParameters": 255,
          "emissive": 0,
          "blockBaseImageName": "",
          "blockType": 0,
          "metadataNote": ""
        },
        {
          "color": 4283124555,
          "materialParameters": 255,
          "emissive": 0,
          "blockBaseImageName": "",
          "blockType": 0,
          "metadataNote": ""
        },
        {
          "color": 4283124555,
          "materialParameters": 255,
          "emissive": 0,
          "blockBaseImageName": "",
          "blockType": 0,
          "metadataNote": ""
        },
        {
          "color": 4283124555,
          "materialParameters": 255,
          "emissive": 0,
          "blockBaseImageName": "",
          "blockType": 0,
          "metadataNote": ""
        },
        {
          "color": 4283124555,
          "materialParameters": 255,
          "emissive": 0,
          "blockBaseImageName": "",
          "blockType": 0,
          "metadataNote": ""
        },
        {
          "color": 4283124555,
          "materialParameters": 255,
          "emissive": 0,
          "blockBaseImageName": "",
          "blockType": 0,
          "metadataNote": ""
        },
        {
          "color": 4283124555,
          "materialParameters": 255,
          "emissive": 0,
          "blockBaseImageName": "",
          "blockType": 0,
          "metadataNote": ""
        },
        {
          "color": 4283124555,
          "materialParameters": 255,
          "emissive": 0,
          "blockBaseImageName": "",
          "blockType": 0,
          "metadataNote": ""
        },
        {
          "color": 4283124555,
          "materialParameters": 255,
          "emissive": 0,
          "blockBaseImageName": "",
          "blockType": 0,
          "metadataNote": ""
        },
        {
          "color": 4283124555,
          "materialParameters": 255,
          "emissive": 0,
          "blockBaseImageName": "",
          "blockType": 0,
          "metadataNote": ""
        },
        {
          "color": 4283124555,
          "materialParameters": 255,
          "emissive": 0,
          "blockBaseImageName": "",
          "blockType": 0,
          "metadataNote": ""
        },
        {
          "color": 4283124555,
          "materialParameters": 255,
          "emissive": 0,
          "blockBaseImageName": "",
          "blockType": 0,
          "metadataNote": ""
        },
        {
          "color": 4283124555,
          "materialParameters": 255,
          "emissive": 0,
          "blockBaseImageName": "",
          "blockType": 0,
          "metadataNote": ""
        },
        {
          "color": 4283124555,
          "materialParameters": 255,
          "emissive": 0,
          "blockBaseImageName": "",
          "blockType": 0,
          "metadataNote": ""
        },
        {
          "color": 4283124555,
          "materialParameters": 255,
          "emissive": 0,
          "blockBaseImageName": "",
          "blockType": 0,
          "metadataNote": ""
        },
        {
          "color": 4283124555,
          "materialParameters": 255,
          "emissive": 0,
          "blockBaseImageName": "",
          "blockType": 0,
          "metadataNote": ""
        },
        {
          "color": 4283124555,
          "materialParameters": 255,
          "emissive": 0,
          "blockBaseImageName": "",
          "blockType": 0,
          "metadataNote": ""
        },
        {
          "color": 4283124555,
          "materialParameters": 255,
          "emissive": 0,
          "blockBaseImageName": "",
          "blockType": 0,
          "metadataNote": ""
        },
        {
          "color": 4283124555,
          "materialParameters": 255,
          "emissive": 0,
          "blockBaseImageName": "",
          "blockType": 0,
          "metadataNote": ""
        },
        {
          "color": 4283124555,
          "materialParameters": 255,
          "emissive": 0,
          "blockBaseImageName": "",
          "blockType": 0,
          "metadataNote": ""
        },
        {
          "color": 4283124555,
          "materialParameters": 255,
          "emissive": 0,
          "blockBaseImageName": "",
          "blockType": 0,
          "metadataNote": ""
        },
        {
          "color": 4283124555,
          "materialParameters": 255,
          "emissive": 0,
          "blockBaseImageName": "",
          "blockType": 0,
          "metadataNote": ""
        },
        {
          "color": 4283124555,
          "materialParameters": 255,
          "emissive": 0,
          "blockBaseImageName": "",
          "blockType": 0,
          "metadataNote": ""
        },
        {
          "color": 4283124555,
          "materialParameters": 255,
          "emissive": 0,
          "blockBaseImageName": "",
          "blockType": 0,
          "metadataNote": ""
        },
        {
          "color": 4283124555,
          "materialParameters": 255,
          "emissive": 0,
          "blockBaseImageName": "",
          "blockType": 0,
          "metadataNote": ""
        },
        {
          "color": 4283124555,
          "materialParameters": 255,
          "emissive": 0,
          "blockBaseImageName": "",
          "blockType": 0,
          "metadataNote": ""
        },
        {
          "color": 4283124555,
          "materialParameters": 255,
          "emissive": 0,
          "blockBaseImageName": "",
          "blockType": 0,
          "metadataNote": ""
        },
        {
          "color": 4283124555,
          "materialParameters": 255,
          "emissive": 0,
          "blockBaseImageName": "",
          "blockType": 0,
          "metadataNote": ""
        },
        {
          "color": 4283124555,
          "materialParameters": 255,
          "emissive": 0,
          "blockBaseImageName": "",
          "blockType": 0,
          "metadataNote": ""
        },
        {
          "color": 4283124555,
          "materialParameters": 255,
          "emissive": 0,
          "blockBaseImageName": "",
          "blockType": 0,
          "metadataNote": ""
        },
        {
          "color": 4283124555,
          "materialParameters": 255,
          "emissive": 0,
          "blockBaseImageName": "",
          "blockType": 0,
          "metadataNote": ""
        },
        {
          "color": 4283124555,
          "materialParameters": 255,
          "emissive": 0,
          "blockBaseImageName": "",
          "blockType": 0,
          "metadataNote": ""
        },
        {
          "color": 4283124555,
          "materialParameters": 255,
          "emissive": 0,
          "blockBaseImageName": "",
          "blockType": 0,
          "metadataNote": ""
        },
        {
          "color": 4283124555,
          "materialParameters": 255,
          "emissive": 0,
          "blockBaseImageName": "",
          "blockType": 0,
          "metadataNote": ""
        },
        {
          "color": 4283124555,
          "materialParameters": 255,
          "emissive": 0,
          "blockBaseImageName": "",
          "blockType": 0,
          "metadataNote": ""
        },
        {
          "color": 4283124555,
          "materialParameters": 255,
          "emissive": 0,
          "blockBaseImageName": "",
          "blockType": 0,
          "metadataNote": ""
        },
        {
          "color": 4283124555,
          "materialParameters": 255,
          "emissive": 0,
          "blockBaseImageName": "",
          "blockType": 0,
          "metadataNote": ""
        },
        {
          "color": 4283124555,
          "materialParameters": 255,
          "emissive": 0,
          "blockBaseImageName": "",
          "blockType": 0,
          "metadataNote": ""
        },
        {
          "color": 4283124555,
          "materialParameters": 255,
          "emissive": 0,
          "blockBaseImageName": "",
          "blockType": 0,
          "metadataNote": ""
        },
        {
          "color": 4283124555,
          "materialParameters": 255,
          "emissive": 0,
          "blockBaseImageName": "",
          "blockType": 0,
          "metadataNote": ""
        },
        {
          "color": 4283124555,
          "materialParameters": 255,
          "emissive": 0,
          "blockBaseImageName": "",
          "blockType": 0,
          "metadataNote": ""
        },
        {
          "color": 4283124555,
          "materialParameters": 255,
          "emissive": 0,
          "blockBaseImageName": "",
          "blockType": 0,
          "metadataNote": ""
        },
        {
          "color": 4283124555,
          "materialParameters": 255,
          "emissive": 0,
          "blockBaseImageName": "",
          "blockType": 0,
          "metadataNote": ""
        },
        {
          "color": 4283124555,
          "materialParameters": 255,
          "emissive": 0,
          "blockBaseImageName": "",
          "blockType": 0,
          "metadataNote": ""
        },
        {
          "color": 4283124555,
          "materialParameters": 255,
          "emissive": 0,
          "blockBaseImageName": "",
          "blockType": 0,
          "metadataNote": ""
        },
        {
          "color": 4283124555,
          "materialParameters": 255,
          "emissive": 0,
          "blockBaseImageName": "",
          "blockType": 0,
          "metadataNote": ""
        },
        {
          "color": 4283124555,
          "materialParameters": 255,
          "emissive": 0,
          "blockBaseImageName": "",
          "blockType": 0,
          "metadataNote": ""
        },
        {
          "color": 4283124555,
          "materialParameters": 255,
          "emissive": 0,
          "blockBaseImageName": "",
          "blockType": 0,
          "metadataNote": ""
        },
        {
          "color": 4283124555,
          "materialParameters": 255,
          "emissive": 0,
          "blockBaseImageName": "",
          "blockType": 0,
          "metadataNote": ""
        },
        {
          "color": 4283124555,
          "materialParameters": 255,
          "emissive": 0,
          "blockBaseImageName": "",
          "blockType": 0,
          "metadataNote": ""
        },
        {
          "color": 4283124555,
          "materialParameters": 255,
          "emissive": 0,
          "blockBaseImageName": "",
          "blockType": 0,
          "metadataNote": ""
        },
        {
          "color": 4283124555,
          "materialParameters": 255,
          "emissive": 0,
          "blockBaseImageName": "",
          "blockType": 0,
          "metadataNote": ""
        },
        {
          "color": 4283124555,
          "materialParameters": 255,
          "emissive": 0,
          "blockBaseImageName": "",
          "blockType": 0,
          "metadataNote": ""
        },
        {
          "color": 4283124555,
          "materialParameters": 255,
          "emissive": 0,
          "blockBaseImageName": "",
          "blockType": 0,
          "metadataNote": ""
        },
        {
          "color": 4283124555,
          "materialParameters": 255,
          "emissive": 0,
          "blockBaseImageName": "",
          "blockType": 0,
          "metadataNote": ""
        },
        {
          "color": 4283124555,
          "materialParameters": 255,
          "emissive": 0,
          "blockBaseImageName": "",
          "blockType": 0,
          "metadataNote": ""
        },
        {
          "color": 4283124555,
          "materialParameters": 255,
          "emissive": 0,
          "blockBaseImageName": "",
          "blockType": 0,
          "metadataNote": ""
        },
        {
          "color": 4283124555,
          "materialParameters": 255,
          "emissive": 0,
          "blockBaseImageName": "",
          "blockType": 0,
          "metadataNote": ""
        },
        {
          "color": 4283124555,
          "materialParameters": 255,
          "emissive": 0,
          "blockBaseImageName": "",
          "blockType": 0,
          "metadataNote": ""
        },
        {
          "color": 4283124555,
          "materialParameters": 255,
          "emissive": 0,
          "blockBaseImageName": "",
          "blockType": 0,
          "metadataNote": ""
        },
        {
          "color": 4283124555,
          "materialParameters": 255,
          "emissive": 0,
          "blockBaseImageName": "",
          "blockType": 0,
          "metadataNote": ""
        },
        {
          "color": 4283124555,
          "materialParameters": 255,
          "emissive": 0,
          "blockBaseImageName": "",
          "blockType": 0,
          "metadataNote": ""
        },
        {
          "color": 4283124555,
          "materialParameters": 255,
          "emissive": 0,
          "blockBaseImageName": "",
          "blockType": 0,
          "metadataNote": ""
        },
        {
          "color": 4283124555,
          "materialParameters": 255,
          "emissive": 0,
          "blockBaseImageName": "",
          "blockType": 0,
          "metadataNote": ""
        },
        {
          "color": 4283124555,
          "materialParameters": 255,
          "emissive": 0,
          "blockBaseImageName": "",
          "blockType": 0,
          "metadataNote": ""
        },
        {
          "color": 4283124555,
          "materialParameters": 255,
          "emissive": 0,
          "blockBaseImageName": "",
          "blockType": 0,
          "metadataNote": ""
        },
        {
          "color": 4283124555,
          "materialParameters": 255,
          "emissive": 0,
          "blockBaseImageName": "",
          "blockType": 0,
          "metadataNote": ""
        },
        {
          "color": 4283124555,
          "materialParameters": 255,
          "emissive": 0,
          "blockBaseImageName": "",
          "blockType": 0,
          "metadataNote": ""
        },
        {
          "color": 4283124555,
          "materialParameters": 255,
          "emissive": 0,
          "blockBaseImageName": "",
          "blockType": 0,
          "metadataNote": ""
        },
        {
          "color": 4283124555,
          "materialParameters": 255,
          "emissive": 0,
          "blockBaseImageName": "",
          "blockType": 0,
          "metadataNote": ""
        },
        {
          "color": 4283124555,
          "materialParameters": 255,
          "emissive": 0,
          "blockBaseImageName": "",
          "blockType": 0,
          "metadataNote": ""
        },
        {
          "color": 4283124555,
          "materialParameters": 255,
          "emissive": 0,
          "blockBaseImageName": "",
          "blockType": 0,
          "metadataNote": ""
        },
        {
          "color": 4283124555,
          "materialParameters": 255,
          "emissive": 0,
          "blockBaseImageName": "",
          "blockType": 0,
          "metadataNote": ""
        },
        {
          "color": 4283124555,
          "materialParameters": 255,
          "emissive": 0,
          "blockBaseImageName": "",
          "blockType": 0,
          "metadataNote": ""
        },
        {
          "color": 4283124555,
          "materialParameters": 255,
          "emissive": 0,
          "blockBaseImageName": "",
          "blockType": 0,
          "metadataNote": ""
        },
        {
          "color": 4283124555,
          "materialParameters": 255,
          "emissive": 0,
          "blockBaseImageName": "",
          "blockType": 0,
          "metadataNote": ""
        },
        {
          "color": 4283124555,
          "materialParameters": 255,
          "emissive": 0,
          "blockBaseImageName": "",
          "blockType": 0,
          "metadataNote": ""
        },
        {
          "color": 4283124555,
          "materialParameters": 255,
          "emissive": 0,
          "blockBaseImageName": "",
          "blockType": 0,
          "metadataNote": ""
        },
        {
          "color": 4283124555,
          "materialParameters": 255,
          "emissive": 0,
          "blockBaseImageName": "",
          "blockType": 0,
          "metadataNote": ""
        },
        {
          "color": 4283124555,
          "materialParameters": 255,
          "emissive": 0,
          "blockBaseImageName": "",
          "blockType": 0,
          "metadataNote": ""
        },
        {
          "color": 4283124555,
          "materialParameters": 255,
          "emissive": 0,
          "blockBaseImageName": "",
          "blockType": 0,
          "metadataNote": ""
        },
        {
          "color": 4283124555,
          "materialParameters": 255,
          "emissive": 0,
          "blockBaseImageName": "",
          "blockType": 0,
          "metadataNote": ""
        },
        {
          "color": 4283124555,
          "materialParameters": 255,
          "emissive": 0,
          "blockBaseImageName": "",
          "blockType": 0,
          "metadataNote": ""
        },
        {
          "color": 4283124555,
          "materialParameters": 255,
          "emissive": 0,
          "blockBaseImageName": "",
          "blockType": 0,
          "metadataNote": ""
        },
        {
          "color": 4283124555,
          "materialParameters": 255,
          "emissive": 0,
          "blockBaseImageName": "",
          "blockType": 0,
          "metadataNote": ""
        },
        {
          "color": 4283124555,
          "materialParameters": 255,
          "emissive": 0,
          "blockBaseImageName": "",
          "blockType": 0,
          "metadataNote": ""
        },
        {
          "color": 4283124555,
          "materialParameters": 255,
          "emissive": 0,
          "blockBaseImageName": "",
          "blockType": 0,
          "metadataNote": ""
        },
        {
          "color": 4283124555,
          "materialParameters": 255,
          "emissive": 0,
          "blockBaseImageName": "",
          "blockType": 0,
          "metadataNote": ""
        },
        {
          "color": 4283124555,
          "materialParameters": 255,
          "emissive": 0,
          "blockBaseImageName": "",
          "blockType": 0,
          "metadataNote": ""
        },
        {
          "color": 4283124555,
          "materialParameters": 255,
          "emissive": 0,
          "blockBaseImageName": "",
          "blockType": 0,
          "metadataNote": ""
        },
        {
          "color": 4283124555,
          "materialParameters": 255,
          "emissive": 0,
          "blockBaseImageName": "",
          "blockType": 0,
          "metadataNote": ""
        },
        {
          "color": 4283124555,
          "materialParameters": 255,
          "emissive": 0,
          "blockBaseImageName": "",
          "blockType": 0,
          "metadataNote": ""
        },
        {
          "color": 4283124555,
          "materialParameters": 255,
          "emissive": 0,
          "blockBaseImageName": "",
          "blockType": 0,
          "metadataNote": ""
        },
        {
          "color": 4283124555,
          "materialParameters": 255,
          "emissive": 0,
          "blockBaseImageName": "",
          "blockType": 0,
          "metadataNote": ""
        },
        {
          "color": 4283124555,
          "materialParameters": 255,
          "emissive": 0,
          "blockBaseImageName": "",
          "blockType": 0,
          "metadataNote": ""
        },
        {
          "color": 4283124555,
          "materialParameters": 255,
          "emissive": 0,
          "blockBaseImageName": "",
          "blockType": 0,
          "metadataNote": ""
        },
        {
          "color": 4283124555,
          "materialParameters": 255,
          "emissive": 0,
          "blockBaseImageName": "",
          "blockType": 0,
          "metadataNote": ""
        },
        {
          "color": 4283124555,
          "materialParameters": 255,
          "emissive": 0,
          "blockBaseImageName": "",
          "blockType": 0,
          "metadataNote": ""
        },
        {
          "color": 4283124555,
          "materialParameters": 255,
          "emissive": 0,
          "blockBaseImageName": "",
          "blockType": 0,
          "metadataNote": ""
        },
        {
          "color": 4283124555,
          "materialParameters": 255,
          "emissive": 0,
          "blockBaseImageName": "",
          "blockType": 0,
          "metadataNote": ""
        },
        {
          "color": 4283124555,
          "materialParameters": 255,
          "emissive": 0,
          "blockBaseImageName": "",
          "blockType": 0,
          "metadataNote": ""
        },
        {
          "color": 4283124555,
          "materialParameters": 255,
          "emissive": 0,
          "blockBaseImageName": "",
          "blockType": 0,
          "metadataNote": ""
        },
        {
          "color": 4283124555,
          "materialParameters": 255,
          "emissive": 0,
          "blockBaseImageName": "",
          "blockType": 0,
          "metadataNote": ""
        },
        {
          "color": 4283124555,
          "materialParameters": 255,
          "emissive": 0,
          "blockBaseImageName": "",
          "blockType": 0,
          "metadataNote": ""
        },
        {
          "color": 4283124555,
          "materialParameters": 255,
          "emissive": 0,
          "blockBaseImageName": "",
          "blockType": 0,
          "metadataNote": ""
        },
        {
          "color": 4283124555,
          "materialParameters": 255,
          "emissive": 0,
          "blockBaseImageName": "",
          "blockType": 0,
          "metadataNote": ""
        },
        {
          "color": 4283124555,
          "materialParameters": 255,
          "emissive": 0,
          "blockBaseImageName": "",
          "blockType": 0,
          "metadataNote": ""
        },
        {
          "color": 4283124555,
          "materialParameters": 255,
          "emissive": 0,
          "blockBaseImageName": "",
          "blockType": 0,
          "metadataNote": ""
        },
        {
          "color": 4283124555,
          "materialParameters": 255,
          "emissive": 0,
          "blockBaseImageName": "",
          "blockType": 0,
          "metadataNote": ""
        },
        {
          "color": 4283124555,
          "materialParameters": 255,
          "emissive": 0,
          "blockBaseImageName": "",
          "blockType": 0,
          "metadataNote": ""
        },
        {
          "color": 4283124555,
          "materialParameters": 255,
          "emissive": 0,
          "blockBaseImageName": "",
          "blockType": 0,
          "metadataNote": ""
        },
        {
          "color": 4283124555,
          "materialParameters": 255,
          "emissive": 0,
          "blockBaseImageName": "",
          "blockType": 0,
          "metadataNote": ""
        },
        {
          "color": 4283124555,
          "materialParameters": 255,
          "emissive": 0,
          "blockBaseImageName": "",
          "blockType": 0,
          "metadataNote": ""
        },
        {
          "color": 4283124555,
          "materialParameters": 255,
          "emissive": 0,
          "blockBaseImageName": "",
          "blockType": 0,
          "metadataNote": ""
        },
        {
          "color": 4283124555,
          "materialParameters": 255,
          "emissive": 0,
          "blockBaseImageName": "",
          "blockType": 0,
          "metadataNote": ""
        },
        {
          "color": 4283124555,
          "materialParameters": 255,
          "emissive": 0,
          "blockBaseImageName": "",
          "blockType": 0,
          "metadataNote": ""
        },
        {
          "color": 4283124555,
          "materialParameters": 255,
          "emissive": 0,
          "blockBaseImageName": "",
          "blockType": 0,
          "metadataNote": ""
        },
        {
          "color": 4283124555,
          "materialParameters": 255,
          "emissive": 0,
          "blockBaseImageName": "",
          "blockType": 0,
          "metadataNote": ""
        },
        {
          "color": 4283124555,
          "materialParameters": 255,
          "emissive": 0,
          "blockBaseImageName": "",
          "blockType": 0,
          "metadataNote": ""
        },
        {
          "color": 4283124555,
          "materialParameters": 255,
          "emissive": 0,
          "blockBaseImageName": "",
          "blockType": 0,
          "metadataNote": ""
        },
        {
          "color": 4283124555,
          "materialParameters": 255,
          "emissive": 0,
          "blockBaseImageName": "",
          "blockType": 0,
          "metadataNote": ""
        },
        {
          "color": 4283124555,
          "materialParameters": 255,
          "emissive": 0,
          "blockBaseImageName": "",
          "blockType": 0,
          "metadataNote": ""
        },
        {
          "color": 4283124555,
          "materialParameters": 255,
          "emissive": 0,
          "blockBaseImageName": "",
          "blockType": 0,
          "metadataNote": ""
        },
        {
          "color": 4283124555,
          "materialParameters": 255,
          "emissive": 0,
          "blockBaseImageName": "",
          "blockType": 0,
          "metadataNote": ""
        },
        {
          "color": 4283124555,
          "materialParameters": 255,
          "emissive": 0,
          "blockBaseImageName": "",
          "blockType": 0,
          "metadataNote": ""
        },
        {
          "color": 4283124555,
          "materialParameters": 255,
          "emissive": 0,
          "blockBaseImageName": "",
          "blockType": 0,
          "metadataNote": ""
        },
        {
          "color": 4283124555,
          "materialParameters": 255,
          "emissive": 0,
          "blockBaseImageName": "",
          "blockType": 0,
          "metadataNote": ""
        },
        {
          "color": 4283124555,
          "materialParameters": 255,
          "emissive": 0,
          "blockBaseImageName": "",
          "blockType": 0,
          "metadataNote": ""
        },
        {
          "color": 4283124555,
          "materialParameters": 255,
          "emissive": 0,
          "blockBaseImageName": "",
          "blockType": 0,
          "metadataNote": ""
        },
        {
          "color": 4283124555,
          "materialParameters": 255,
          "emissive": 0,
          "blockBaseImageName": "",
          "blockType": 0,
          "metadataNote": ""
        },
        {
          "color": 4283124555,
          "materialParameters": 255,
          "emissive": 0,
          "blockBaseImageName": "",
          "blockType": 0,
          "metadataNote": ""
        },
        {
          "color": 4283124555,
          "materialParameters": 255,
          "emissive": 0,
          "blockBaseImageName": "",
          "blockType": 0,
          "metadataNote": ""
        },
        {
          "color": 4283124555,
          "materialParameters": 255,
          "emissive": 0,
          "blockBaseImageName": "",
          "blockType": 0,
          "metadataNote": ""
        },
        {
          "color": 4283124555,
          "materialParameters": 255,
          "emissive": 0,
          "blockBaseImageName": "",
          "blockType": 0,
          "metadataNote": ""
        },
        {
          "color": 4283124555,
          "materialParameters": 255,
          "emissive": 0,
          "blockBaseImageName": "",
          "blockType": 0,
          "metadataNote": ""
        },
        {
          "color": 4283124555,
          "materialParameters": 255,
          "emissive": 0,
          "blockBaseImageName": "",
          "blockType": 0,
          "metadataNote": ""
        },
        {
          "color": 4283124555,
          "materialParameters": 255,
          "emissive": 0,
          "blockBaseImageName": "",
          "blockType": 0,
          "metadataNote": ""
        },
        {
          "color": 4283124555,
          "materialParameters": 255,
          "emissive": 0,
          "blockBaseImageName": "",
          "blockType": 0,
          "metadataNote": ""
        },
        {
          "color": 4283124555,
          "materialParameters": 255,
          "emissive": 0,
          "blockBaseImageName": "",
          "blockType": 0,
          "metadataNote": ""
        },
        {
          "color": 4283124555,
          "materialParameters": 255,
          "emissive": 0,
          "blockBaseImageName": "",
          "blockType": 0,
          "metadataNote": ""
        },
        {
          "color": 4283124555,
          "materialParameters": 255,
          "emissive": 0,
          "blockBaseImageName": "",
          "blockType": 0,
          "metadataNote": ""
        },
        {
          "color": 4283124555,
          "materialParameters": 255,
          "emissive": 0,
          "blockBaseImageName": "",
          "blockType": 0,
          "metadataNote": ""
        },
        {
          "color": 4283124555,
          "materialParameters": 255,
          "emissive": 0,
          "blockBaseImageName": "",
          "blockType": 0,
          "metadataNote": ""
        },
        {
          "color": 4283124555,
          "materialParameters": 255,
          "emissive": 0,
          "blockBaseImageName": "",
          "blockType": 0,
          "metadataNote": ""
        },
        {
          "color": 4283124555,
          "materialParameters": 255,
          "emissive": 0,
          "blockBaseImageName": "",
          "blockType": 0,
          "metadataNote": ""
        },
        {
          "color": 4283124555,
          "materialParameters": 255,
          "emissive": 0,
          "blockBaseImageName": "",
          "blockType": 0,
          "metadataNote": ""
        },
        {
          "color": 4283124555,
          "materialParameters": 255,
          "emissive": 0,
          "blockBaseImageName": "",
          "blockType": 0,
          "metadataNote": ""
        }
      ]
    }
  }
}